ansible_less/__init__.py
ansible_less/tests/test_group_by_hosts.py
ansible_less/tests/test_line_filters.py
ansible_less/tools/__init__.py
ansible_less/tools/ansible_less_cli.py
ansible_less/tools/test-process.py
ansible_less-1.0.dist-info/METADATA
ansible_less-1.0.dist-info/WHEEL
ansible_less-1.0.dist-info/entry_points.txt
ansible_less-1.0.dist-info/RECORD
