Metadata-Version: 2.4
Name: ansible-less
Version: 1.0
Summary: DESCR
Project-URL: Homepage, https://github.com/hardaker/ansible-less
Author-email: Wes Hardaker <opensource@hardakers.net>
Classifier: Operating System :: OS Independent
Classifier: Programming Language :: Python :: 3
Requires-Python: >=3.7
Requires-Dist: argparse-with-config
Requires-Dist: rich
Requires-Dist: rich-argparse
Requires-Dist: rich-logging
